classto/__init__.py
classto/image_labeler.py
classto/main.py
classto/utils.py
classto/static/favicon.png
classto/static/css/input.css
classto/static/css/tailwind.css
classto/static/js/alpine-3.14.9.min.js
classto/templates/index.html
classto-2.0.0.dist-info/licenses/LICENSE
classto-2.0.0.dist-info/METADATA
classto-2.0.0.dist-info/WHEEL
classto-2.0.0.dist-info/top_level.txt
classto-2.0.0.dist-info/RECORD
