Metadata-Version: 2.4
Name: classto
Version: 2.0.0
Summary: A Python library for browser-based manual image classification
Author: Simon Hardmeier
License-Expression: MIT
Requires-Python: >=3.7
License-File: LICENSE
Requires-Dist: flask>=2.2
Dynamic: license-file
